LICENSE
MANIFEST.in
README.md
setup.py
nrftool/__init__.py
nrftool/cmdline.py
nrftool.egg-info/PKG-INFO
nrftool.egg-info/SOURCES.txt
nrftool.egg-info/dependency_links.txt
nrftool.egg-info/entry_points.txt
nrftool.egg-info/top_level.txt
nrftool/command/__init__.py
nrftool/command/base.py
nrftool/command/erase.py
nrftool/command/flash.py
nrftool/command/jlink.py
nrftool/script/erase.jlink
nrftool/script/flash.jlink