Metadata-Version: 1.1
Name: nrftool
Version: 0.1.0
Summary: A tool to flash and erase nRF devices
Home-page: https://github.com/pauloborges/nrftool
Author: Paulo Borges
Author-email: pauloborgesfilho@gmail.com
License: MIT
Platform: UNKNOWN
Classifier: Development Status :: 3 - Alpha
Classifier: Environment :: Console
Classifier: License :: OSI Approved :: MIT License
Classifier: Natural Language :: English
Classifier: Operating System :: POSIX :: Linux
Classifier: Programming Language :: Python :: 2
